xaal/__init__.py
xaal/gtknotify/__init__.py
xaal/gtknotify/__main__.py
xaal/gtknotify/dev.py
xaal/gtknotify/test.py
xaal_gtknotify-0.1.2.dist-info/METADATA
xaal_gtknotify-0.1.2.dist-info/WHEEL
xaal_gtknotify-0.1.2.dist-info/top_level.txt
xaal_gtknotify-0.1.2.dist-info/RECORD
